[
  {
    "id": 1754025312395.7322,
    "timestamp": "2025-08-01T05:15:12.395Z",
    "type": "info",
    "level": "info",
    "message": [
      "🛠️ 開發模式：控制台增強功能已啟用"
    ],
    "component": "Cocktail-Bar-POS",
    "url": "http://localhost:5173/"
  },
  {
    "id": 1754025312397.3992,
    "timestamp": "2025-08-01T05:15:12.397Z",
    "type": "info",
    "level": "info",
    "message": [
      "💡 使用 __console_interceptor__.report() 查看日誌報告"
    ],
    "component": "Cocktail-Bar-POS",
    "url": "http://localhost:5173/"
  },
  {
    "id": 1754025312398.041,
    "timestamp": "2025-08-01T05:15:12.398Z",
    "type": "log",
    "level": "info",
    "message": [
      "🍸 調酒酒吧 POS 系統啟動"
    ],
    "component": "Cocktail-Bar-POS",
    "url": "http://localhost:5173/"
  },
  {
    "id": 1754025312400.7827,
    "timestamp": "2025-08-01T05:15:12.400Z",
    "type": "log",
    "level": "info",
    "message": [
      "📊 Console 日誌攔截器已啟用 (Vite 模式)"
    ],
    "component": "Cocktail-Bar-POS",
    "url": "http://localhost:5173/"
  },
  {
    "id": 1754025312401.568,
    "timestamp": "2025-08-01T05:15:12.401Z",
    "type": "log",
    "level": "info",
    "message": [
      "🛠️ 使用 __console_interceptor__.report() 查看報告"
    ],
    "component": "Cocktail-Bar-POS",
    "url": "http://localhost:5173/"
  },
  {
    "id": 1754025312461.1975,
    "timestamp": "2025-08-01T05:15:12.461Z",
    "type": "log",
    "level": "info",
    "message": [
      "App.tsx: Starting app store initialization..."
    ],
    "component": "Cocktail-Bar-POS",
    "url": "http://localhost:5173/"
  },
  {
    "id": 1754025312463.3552,
    "timestamp": "2025-08-01T05:15:12.463Z",
    "type": "log",
    "level": "info",
    "message": [
      "appStore: Initializing all child stores..."
    ],
    "component": "Cocktail-Bar-POS",
    "url": "http://localhost:5173/"
  },
  {
    "id": 1754025312464.1377,
    "timestamp": "2025-08-01T05:15:12.464Z",
    "type": "log",
    "level": "info",
    "message": [
      "orderStore: Initializing..."
    ],
    "component": "Cocktail-Bar-POS",
    "url": "http://localhost:5173/"
  },
  {
    "id": 1754025312466.6223,
    "timestamp": "2025-08-01T05:15:12.466Z",
    "type": "warn",
    "level": "warn",
    "message": [
      "Capacitor Preferences not available, falling back to localStorage"
    ],
    "component": "Cocktail-Bar-POS",
    "url": "http://localhost:5173/"
  },
  {
    "id": 1754025312467.1377,
    "timestamp": "2025-08-01T05:15:12.467Z",
    "type": "log",
    "level": "info",
    "message": [
      "🌐 Using Web Storage (localStorage)"
    ],
    "component": "Cocktail-Bar-POS",
    "url": "http://localhost:5173/"
  },
  {
    "id": 1754025312469.5999,
    "timestamp": "2025-08-01T05:15:12.469Z",
    "type": "log",
    "level": "info",
    "message": [
      "App.tsx: App store initialization triggered."
    ],
    "component": "Cocktail-Bar-POS",
    "url": "http://localhost:5173/"
  },
  {
    "id": 1754025312471.9976,
    "timestamp": "2025-08-01T05:15:12.471Z",
    "type": "log",
    "level": "info",
    "message": [
      "App.tsx: Starting app store initialization..."
    ],
    "component": "Cocktail-Bar-POS",
    "url": "http://localhost:5173/"
  },
  {
    "id": 1754025312473.488,
    "timestamp": "2025-08-01T05:15:12.473Z",
    "type": "log",
    "level": "info",
    "message": [
      "appStore: Already initialized or initializing, skipping..."
    ],
    "component": "Cocktail-Bar-POS",
    "url": "http://localhost:5173/"
  },
  {
    "id": 1754025312474.9468,
    "timestamp": "2025-08-01T05:15:12.474Z",
    "type": "log",
    "level": "info",
    "message": [
      "App.tsx: App store initialization triggered."
    ],
    "component": "Cocktail-Bar-POS",
    "url": "http://localhost:5173/"
  },
  {
    "id": 1754025312477.3906,
    "timestamp": "2025-08-01T05:15:12.477Z",
    "type": "log",
    "level": "info",
    "message": [
      "orderStore: Orders loaded successfully."
    ],
    "component": "Cocktail-Bar-POS",
    "url": "http://localhost:5173/"
  },
  {
    "id": 1754025312482.7043,
    "timestamp": "2025-08-01T05:15:12.482Z",
    "type": "error",
    "level": "error",
    "message": [
      "The result of getSnapshot should be cached to avoid an infinite loop"
    ],
    "component": "Cocktail-Bar-POS",
    "url": "http://localhost:5173/"
  },
  {
    "id": 1754025312872.8032,
    "timestamp": "2025-08-01T05:15:12.872Z",
    "type": "error",
    "level": "error",
    "message": [
      "%o\n\n%s\n\n%s\n",
      {},
      "The above error occurred in one of your React components.",
      "React will try to recreate this component tree from scratch using the error boundary you provided, ErrorBoundary."
    ],
    "component": "Cocktail-Bar-POS",
    "url": "http://localhost:5173/"
  },
  {
    "id": 1754025312874.2214,
    "timestamp": "2025-08-01T05:15:12.874Z",
    "type": "error",
    "level": "error",
    "message": [
      "ErrorBoundary caught an error:",
      {},
      {
        "componentStack": "\n    at http://localhost:5173/src/components/Sidebar.tsx?t=1754025136010:21:3\n    at ErrorBoundary (http://localhost:5173/src/components/ErrorBoundary.tsx:7:5)\n    at div (<anonymous>)\n    at AppContent (http://localhost:5173/src/App.tsx?t=1754025255079:35:25)\n    at ErrorBoundary (http://localhost:5173/src/components/ErrorBoundary.tsx:7:5)\n    at GlobalErrorBoundary (http://localhost:5173/src/components/ErrorBoundary/GlobalErrorBoundary.tsx:7:5)\n    at App (<anonymous>)"
      }
    ],
    "component": "Cocktail-Bar-POS",
    "url": "http://localhost:5173/"
  },
  {
    "id": 1754025312876.2202,
    "timestamp": "2025-08-01T05:15:12.876Z",
    "type": "log",
    "level": "info",
    "message": [
      "appStore: All child stores initialized successfully."
    ],
    "component": "Cocktail-Bar-POS",
    "url": "http://localhost:5173/"
  }
]